[
 {"slug":"first-night","type":"guide","title":"Как пережить первую ночь","description":"От первого дерева до безопасного убежища — маршрут для новичка.","date":"10 июля 2026","readTime":"7 мин","category":"Начало игры","image":"/images/minecraft-hero.png","content":["Соберите несколько брёвен и превратите их в доски. Создайте верстак, деревянную кирку и сразу добудьте камень.","До заката найдите уголь или сделайте древесный уголь. Освещённое укрытие защищает от появления враждебных мобов.","Наутро отметьте координаты базы и начните искать железо для щита, ведра и полного набора инструментов."]},
 {"slug":"best-settings","type":"guide","title":"Лучшие настройки Minecraft","description":"Баланс красивой картинки, удобного управления и стабильной игры.","date":"8 июля 2026","readTime":"6 мин","category":"Настройки","image":"/images/trial-chambers.png","content":["Начните с дальности прорисовки 12–16 чанков и постепенно увеличивайте её.","Отключите покачивание камеры, если оно мешает в бою, и настройте чувствительность мыши.","Используйте полноэкранный режим и родное разрешение дисплея для чёткого изображения."]},
 {"slug":"boost-fps","type":"guide","title":"Как повысить FPS","description":"Практические способы убрать лаги без потери атмосферы.","date":"6 июля 2026","readTime":"8 мин","category":"Оптимизация","image":"/images/creatures.png","content":["Уменьшите дальность симуляции отдельно от дальности прорисовки.","Снизьте качество частиц и облаков, отключите тени сущностей.","Закройте фоновые приложения и убедитесь, что игра использует дискретную видеокарту."]},
 {"slug":"best-seeds","type":"guide","title":"Лучшие сиды для выживания","description":"Шесть миров с деревнями, горами и полезными структурами рядом.","date":"4 июля 2026","readTime":"10 мин","category":"Миры","image":"/images/minecraft-hero.png","content":["Сид 69420017852762830 создаёт живописную долину, окружённую горами.","Проверяйте совпадение версии и издания: генерация Java и Bedrock может различаться.","Перед большим проектом изучите мир в копии и отметьте координаты ключевых структур."]},
 {"slug":"install-mods","type":"guide","title":"Как установить моды","description":"Безопасная установка загрузчика и совместимых модификаций.","date":"2 июля 2026","readTime":"9 мин","category":"Модификации","image":"/images/trial-chambers.png","content":["Сделайте резервную копию миров и проверьте точную версию игры.","Выберите Fabric, NeoForge или Forge — мод должен быть создан для вашего загрузчика.","Скачивайте файлы только с известных каталогов и запускайте игру с новым профилем."]},
 {"slug":"create-server","type":"guide","title":"Как создать свой сервер","description":"Локальный сервер Java Edition: от файла запуска до белого списка.","date":"30 июня 2026","readTime":"12 мин","category":"Серверы","image":"/images/creatures.png","content":["Скачайте официальный server.jar, примите EULA и выделите отдельную папку.","Включите whitelist и регулярно создавайте резервные копии мира.","Для друзей из интернета настройте порт только при понимании сетевой безопасности."]},
 {"slug":"tricky-trials-guide","type":"news","title":"Tricky Trials: полный разбор камер","description":"Как устроены испытания, хранилища и зловещие события.","date":"12 июля 2026","readTime":"11 мин","category":"Обновления","image":"/images/trial-chambers.png","content":["Испытательные камеры генерируются под землёй и состоят из процедурно соединённых залов.","Сложность спавнеров учитывает число игроков рядом, а награды выдаются каждому участнику.","Зловещая бутылочка запускает усиленное испытание с более ценной добычей."]},
 {"slug":"world-design","type":"news","title":"Почему мир Minecraft всегда узнаваем","description":"Разбираем язык кубов, света и бесконечного исследования.","date":"28 июня 2026","readTime":"5 мин","category":"Культура","image":"/images/minecraft-hero.png","content":["Ограниченная геометрия превращает каждый блок в понятную единицу дизайна.","Процедурная генерация создаёт истории через соседство биомов, структур и ресурсов.","Игрок не только исследует мир, но и переписывает его архитектуру."]}
]
